{
  "name": "Дистилятор",
  "category": "devices",
  "icon": "bewitchment:distillery",
  "pages": [
	{
	  "type": "text",
	  "text": "Используется для приготовления паров более высокого уровня, чем те, что может производить Ведьмовская Печь. Некоторые другие соединения также могут быть созданы с помощью этого устройства. Дистилятор требует магической энергии и использует Огненный Порошок в качестве топлива."
	},
	{
	  "type": "crafting",
	  "recipe": "bewitchment:distillery"
	},
	{
	  "type": "bewitchment:distillery_recipe",
	  "recipe": "bewitchment:cleansing_balm",
	  "text": "Бальзам с очищающей силой"
	},
	{
	  "type": "bewitchment:distillery_recipe",
	  "recipe": "bewitchment:demonic_elixir",
	  "text": "Грязная смесь, наполненная сущностью демона"
	},
	{
	  "type": "bewitchment:distillery_recipe",
	  "recipe": "bewitchment:fiery_unguent",
	  "text": "Get your spicy memes here"
	},
	{
	  "type": "bewitchment:distillery_recipe",
	  "recipe": "bewitchment:bottled_frostfire",
	  "text": "Странный анти-огонь, холодный на ощупь. Когда размещён на блоке, может переплавлять железную руду в Холодное Железо, если бросить руду в огонь"
	}
  ]
}
